Workbook

Sheet Ventas_Raw
A1: ID_Transaccion | B1: Fecha | C1: Categoria | D1: Producto | E1: Precio | F1: Canal | G1: Region
A2: VT001 | B2: 2024-10-01 | C2: electrónica | D2: Audífonos Bluetooth | E2: 45000 | F2: web | G2: Metropolitana
A3: VT002 | B3: 2024-10-01 | C3: HOGAR | D3: Aspiradora Robot | E3: 189000 | F3: App | G3: Valparaíso
A4: VT003 | B4: 2024-10-02 | C4: Moda | D4: Zapatillas Running | E4: 65000 | F4: WEB
A5: VT004 | B5: 2024-10-02 | C5: Deportes | D5: Pelota de Fútbol | E5: 25000 | F5: app | G5: Biobío
A6: VT005 | B6: 2024-10-03 | C6: ELECTRÓNICA | D6: Mouse Gaming | E6: 38000 | F6: web | G6: Metropolitana
A7: VT006 | B7: 2024-10-03 | C7: hogar | D7: Juego de Sábanas | E7: 42000 | F7: móvil
A8: VT001 | B8: 2024-10-01 | C8: electrónica | D8: Audífonos Bluetooth | E8: 45000 | F8: web | G8: Metropolitana
A9: VT007 | B9: 2024-10-04 | C9: Moda | D9: Chaqueta Invierno | E9: 95000 | F9: Web | G9: Araucanía
A10: VT008 | B10: 2024-10-04 | C10: deportes | D10: Bicicleta MTB | E10: 320000 | F10: APP | G10: Metropolitana
A11: VT009 | B11: 2024-10-05 | C11: Electrónica | D11: Smart TV 55" | E11: 450000 | F11: web | G11: Valparaíso
A12: VT010 | B12: 2024-10-05 | C12: MODA | D12: Jeans Slim Fit | E12: 52000 | F12: app
A13: VT011 | B13: 2024-10-06 | C13: Hogar | D13: Microondas Digital | E13: 85000 | F13: Web | G13: Coquimbo
A14: VT012 | B14: 2024-10-06 | C14: deportes | D14: Pesas Ajustables | E14: 78000 | F14: WEB | G14: Metropolitana
A15: VT013 | B15: 2024-10-07 | C15: Electrónica | D15: Tablet 10" | E15: 185000 | F15: app | G15: Biobío
A16: VT014 | B16: 2024-10-07 | C16: moda | D16: Cartera Cuero | E16: 48000 | F16: móvil
A17: VT015 | B17: 2024-10-08 | C17: HOGAR | D17: Cafetera Express | E17: 125000 | F17: Web | G17: Valparaíso
A18: VT016 | B18: 2024-10-08 | C18: Deportes | D18: Cuerda para Saltar | E18: 12000 | F18: app | G18: Metropolitana
A19: VT017 | B19: 2024-10-09 | C19: electrónica | D19: Cargador Inalámbrico | E19: 28000 | F19: WEB | G19: Araucanía
A20: VT018 | B20: 2024-10-09 | C20: Moda | D20: Reloj Deportivo | E20: 110000 | F20: Web
A21: VT019 | B21: 2024-10-10 | C21: hogar | D21: Set Ollas Acero | E21: 95000 | F21: app | G21: Coquimbo
A22: VT020 | B22: 2024-10-10 | C22: Deportes | D22: Colchoneta Yoga | E22: 32000 | F22: móvil | G22: Metropolitana
A23: VT021 | B23: 2024-10-11 | C23: ELECTRÓNICA | D23: Teclado Mecánico | E23: 72000 | F23: web | G23: Valparaíso
A24: VT022 | B24: 2024-10-11 | C24: Moda | D24: Mochila Laptop | E24: 58000 | F24: App | G24: Biobío
A25: VT013 | B25: 2024-10-07 | C25: Electrónica | D25: Tablet 10" | E25: 185000 | F25: app | G25: Biobío
A26: VT023 | B26: 2024-10-12 | C26: hogar | D26: Ventilador Torre | E26: 68000 | F26: WEB
A27: VT024 | B27: 2024-10-12 | C27: deportes | D27: Guantes Gimnasio | E27: 18000 | F27: app | G27: Metropolitana
A28: VT025 | B28: 2024-10-13 | C28: Electrónica | D28: Parlante Bluetooth | E28: 55000 | F28: Web | G28: Araucanía
A29: VT026 | B29: 2024-10-13 | C29: MODA | D29: Polera Deportiva | E29: 28000 | F29: móvil | G29: Valparaíso
A30: VT027 | B30: 2024-10-14 | C30: Hogar | D30: Plancha Vapor | E30: 45000 | F30: web
A31: VT028 | B31: 2024-10-14 | C31: Deportes | D31: Bolso Deporte | E31: 38000 | F31: APP | G31: Coquimbo
A32: VT029 | B32: 2024-10-15 | C32: electrónica | D32: Webcam HD | E32: 62000 | F32: Web | G32: Metropolitana
A33: VT030 | B33: 2024-10-15 | C33: moda | D33: Gorro Invierno | E33: 22000 | F33: app | G33: Biobío

Sheet Ventas_Limpias
A1: ID_Transaccion | B1: Fecha | C1: Mes | D1: Categoria | E1: Producto | F1: Precio | G1: Canal | H1: Region
A2: VT001 | B2: 45566 | C2: =TEXT(B2,"mmmm") -> octubre | D2: Electrónica | E2: Audífonos Bluetooth | F2: 45000 | G2: Web | H2: Metropolitana
A3: VT002 | B3: 45566 | C3: =TEXT(B3,"mmmm") -> octubre | D3: Hogar | E3: Aspiradora Robot | F3: 189000 | G3: App | H3: Valparaíso
A4: VT003 | B4: 45567 | C4: =TEXT(B4,"mmmm") -> octubre | D4: Moda | E4: Zapatillas Running | F4: 65000 | G4: Web | H4: No especificado
A5: VT004 | B5: 45567 | C5: =TEXT(B5,"mmmm") -> octubre | D5: Deportes | E5: Pelota de Fútbol | F5: 25000 | G5: App | H5: Biobío
A6: VT005 | B6: 45568 | C6: =TEXT(B6,"mmmm") -> octubre | D6: Electrónica | E6: Mouse Gaming | F6: 38000 | G6: Web | H6: Metropolitana
A7: VT006 | B7: 45568 | C7: =TEXT(B7,"mmmm") -> octubre | D7: Hogar | E7: Juego de Sábanas | F7: 42000 | G7: App | H7: No especificado
A8: VT007 | B8: 45566 | C8: =TEXT(B8,"mmmm") -> octubre | D8: Electrónica | E8: Audífonos Bluetooth | F8: 45000 | G8: Web | H8: Metropolitana
A9: VT008 | B9: 45569 | C9: =TEXT(B9,"mmmm") -> octubre | D9: Moda | E9: Chaqueta Invierno | F9: 95000 | G9: Web | H9: Araucanía
A10: VT009 | B10: 45569 | C10: =TEXT(B10,"mmmm") -> octubre | D10: Deportes | E10: Bicicleta MTB | F10: 320000 | G10: App | H10: Metropolitana
A11: VT010 | B11: 45570 | C11: =TEXT(B11,"mmmm") -> octubre | D11: Electrónica | E11: Smart TV 55" | F11: 450000 | G11: Web | H11: Valparaíso
A12: VT011 | B12: 45570 | C12: =TEXT(B12,"mmmm") -> octubre | D12: Moda | E12: Jeans Slim Fit | F12: 52000 | G12: App | H12: No especificado
A13: VT012 | B13: 45571 | C13: =TEXT(B13,"mmmm") -> octubre | D13: Hogar | E13: Microondas Digital | F13: 85000 | G13: Web | H13: Coquimbo
... A31: VT030 | B31: 45579 | C31: =TEXT(B31,"mmmm") -> octubre | D31: Deportes | E31: Bolso Deporte | F31: 38000 | G31: App | H31: Coquimbo

Sheet Análisis_Ventas
B2: Total de ventas por categoría | E2: ID_Transaccion | F2: Fecha | G2: Categoria | H2: Producto | I2: Precio | J2: Canal | K2: Region | L2: Clasificación
B3: Categoría | C3: Total Ventas | E3: VT001 | F3: 2024-10-01 | G3: Electrónica | H3: Audífonos Bluetooth | I3: 45000 | J3: Web | K3: Metropolitana | L3: =IF(I3>75000,"Alta",IF(I3>=30000,"Media","Baja")) -> Media
B4: Electrónica | C4: =SUMIF(Ventas_Limpias!D:D,B4,Ventas_Limpias!F:F) -> 1103000 | E4: VT002 | F4: 2024-10-01 | G4: Hogar | H4: Aspiradora Robot | I4: 189000 | J4: App | K4: Valparaíso | L4: =IF(I4>75000,"Alta",IF(I4>=30000,"Media","Baja")) -> Alta
B5: Hogar | C5: =SUMIF(Ventas_Limpias!D:D,B5,Ventas_Limpias!F:F) -> 649000 | E5: VT003 | F5: 2024-10-02 | G5: Moda | H5: Zapatillas Running | I5: 65000 | J5: Web | K5: No especificado | L5: =IF(I5>75000,"Alta",IF(I5>=30000,"Media","Baja")) -> Media
B6: Moda | C6: =SUMIF(Ventas_Limpias!D:D,B6,Ventas_Limpias!F:F) -> 456000 | E6: VT004 | F6: 2024-10-02 | G6: Deportes | H6: Pelota de Fútbol | I6: 25000 | J6: App | K6: Biobío | L6: =IF(I6>75000,"Alta",IF(I6>=30000,"Media","Baja")) -> Baja
B7: Deportes | C7: =SUMIF(Ventas_Limpias!D:D,B7,Ventas_Limpias!F:F) -> 523000 | E7: VT005 | F7: 2024-10-03 | G7: Electrónica | H7: Mouse Gaming | I7: 38000 | J7: Web | K7: Metropolitana | L7: =IF(I7>75000,"Alta",IF(I7>=30000,"Media","Baja")) -> Media
E8: VT006 | F8: 2024-10-03 | G8: Hogar | H8: Juego de Sábanas | I8: 42000 | J8: App | K8: No especificado | L8: =IF(I8>75000,"Alta",IF(I8>=30000,"Media","Baja")) -> Media
B9: Ticket promedio por canal | E9: VT007 | F9: 2024-10-01 | G9: Electrónica | H9: Audífonos Bluetooth | I9: 45000 | J9: Web | K9: Metropolitana | L9: =IF(I9>75000,"Alta",IF(I9>=30000,"Media","Baja")) -> Media
B10: Canal | C10: Ticket Promedio | E10: VT008 | F10: 2024-10-04 | G10: Moda | H10: Chaqueta Invierno | I10: 95000 | J10: Web | K10: Araucanía | L10: =IF(I10>75000,"Alta",IF(I10>=30000,"Media","Baja")) -> Alta
B11: Web | C11: =AVERAGEIF(Ventas_Limpias!G:G, B11, Ventas_Limpias!F:F) -> 93600 | E11: VT009 | F11: 2024-10-04 | G11: Deportes | H11: Bicicleta MTB | I11: 320000 | J11: App | K11: Metropolitana | L11: =IF(I11>75000,"Alta",IF(I11>=30000,"Media","Baja")) -> Alta
B12: App | C12: =AVERAGEIF(Ventas_Limpias!G:G, B12, Ventas_Limpias!F:F) -> 88466.667 | E12: VT010 | F12: 2024-10-05 | G12: Electrónica | H12: Smart TV 55" | I12: 450000 | J12: Web | K12: Valparaíso | L12: =IF(I12>75000,"Alta",IF(I12>=30000,"Media","Baja")) -> Alta
E13: VT011 | F13: 2024-10-05 | G13: Moda | H13: Jeans Slim Fit | I13: 52000 | J13: App | K13: No especificado | L13: =IF(I13>75000,"Alta",IF(I13>=30000,"Media","Baja")) -> Media
B14: Transacciones > $50.000 | E14: VT012 | F14: 2024-10-06 | G14: Hogar | H14: Microondas Digital | I14: 85000 | J14: Web | K14: Coquimbo | L14: =IF(I14>75000,"Alta",IF(I14>=30000,"Media","Baja")) -> Alta
B15: =COUNTIF(Ventas_Limpias!F:F,">50000") -> 17 | E15: VT013 | F15: 2024-10-06 | G15: Deportes | H15: Pesas Ajustables | I15: 78000 | J15: Web | K15: Metropolitana | L15: =IF(I15>75000,"Alta",IF(I15>=30000,"Media","Baja")) -> Alta
E16: VT014 | F16: 2024-10-07 | G16: Electrónica | H16: Tablet 10" | I16: 185000 | J16: App | K16: Biobío | L16: =IF(I16>75000,"Alta",IF(I16>=30000,"Media","Baja")) -> Alta
E17: VT015 | F17: 2024-10-07 | G17: Moda | H17: Cartera Cuero | I17: 48000 | J17: App | K17: No especificado | L17: =IF(I17>75000,"Alta",IF(I17>=30000,"Media","Baja")) -> Media
E18: VT016 | F18: 2024-10-08 | G18: Hogar | H18: Cafetera Express | I18: 125000 | J18: Web | K18: Valparaíso | L18: =IF(I18>75000,"Alta",IF(I18>=30000,"Media","Baja")) -> Alta
E19: VT017 | F19: 2024-10-08 | G19: Deportes | H19: Cuerda para Saltar | I19: 12000 | J19: App | K19: Metropolitana | L19: =IF(I19>75000,"Alta",IF(I19>=30000,"Media","Baja")) -> Baja
E20: VT018 | F20: 2024-10-09 | G20: Electrónica | H20: Cargador Inalámbrico | I20: 28000 | J20: Web | K20: Araucanía | L20: =IF(I20>75000,"Alta",IF(I20>=30000,"Media","Baja")) -> Baja
E21: VT019 | F21: 2024-10-09 | G21: Moda | H21: Reloj Deportivo | I21: 110000 | J21: Web | K21: No especificado | L21: =IF(I21>75000,"Alta",IF(I21>=30000,"Media","Baja")) -> Alta
E22: VT020 | F22: 2024-10-10 | G22: Hogar | H22: Set Ollas Acero | I22: 95000 | J22: App | K22: Coquimbo | L22: =IF(I22>75000,"Alta",IF(I22>=30000,"Media","Baja")) -> Alta
E23: VT021 | F23: 2024-10-10 | G23: Deportes | H23: Colchoneta Yoga | I23: 32000 | J23: App | K23: Metropolitana | L23: =IF(I23>75000,"Alta",IF(I23>=30000,"Media","Baja")) -> Media
E24: VT022 | F24: 2024-10-11 | G24: Electrónica | H24: Teclado Mecánico | I24: 72000 | J24: Web | K24: Valparaíso | L24: =IF(I24>75000,"Alta",IF(I24>=30000,"Media","Baja")) -> Media
E25: VT023 | F25: 2024-10-11 | G25: Moda | H25: Mochila Laptop | I25: 58000 | J25: App | K25: Biobío | L25: =IF(I25>75000,"Alta",IF(I25>=30000,"Media","Baja")) -> Media
E26: VT024 | F26: 2024-10-07 | G26: Electrónica | H26: Tablet 10" | I26: 185000 | J26: App | K26: Biobío | L26: =IF(I26>75000,"Alta",IF(I26>=30000,"Media","Baja")) -> Alta
E27: VT025 | F27: 2024-10-12 | G27: Hogar | H27: Ventilador Torre | I27: 68000 | J27: Web | K27: No especificado | L27: =IF(I27>75000,"Alta",IF(I27>=30000,"Media","Baja")) -> Media
... E32: VT030 | F32: 2024-10-14 | G32: Deportes | H32: Bolso Deporte | I32: 38000 | J32: App | K32: Coquimbo | L32: =IF(I32>75000,"Alta",IF(I32>=30000,"Media","Baja")) -> Media

Sheet Dashboard
A5: Ventas totales por Categoría y Canal

Sheet Conclusiones
A1: Conclusiones
A2: El análisis de ventas muestra que la categoría Electrónica es la que genera mayores ingresos, con un total de $1.103.000. Este resultado está impulsado principalmente por el canal Web, que presenta un desempeño significativamente superior al canal App en esta categoría. En cuanto al comportamiento de los tickets de compra, se observa que el canal Web tiende a concentrar ventas de mayor valor, mientras que App presenta un comportamiento más equilibrado o ligeramente inferior en montos promedio. Esto sugiere que los usuarios prefieren realizar compras de mayor valor a través de la web, posiblemente por mayor confianza o facilidad de uso. Durante el proceso de limpieza de datos, se identificaron varios problemas de calidad, incluyendo registros duplicados, inconsistencias en los nombres de categorías (uso de mayúsculas y espacios), variaciones en el campo canal (web, WEB, móvil) y valores faltantes en la región. Estos fueron corregidos mediante la eliminación de duplicados, estandarización de texto, normalización de canales a “Web” y “App”, y completando valores faltantes con “No especificado”. Como recomendaciones, primero, potenciar el canal Web para categorías de alto valor como Electrónica, optimizando la experiencia de compra y promociones específicas. Segundo, fortalecer el canal App mediante estrategias de incentivo, como descuentos exclusivos o mejoras en la usabilidad, para aumentar el ticket promedio y la conversión.
